ezrest/__init__.py
ezrest/objects.py
ezrest/requests.py
ezrest-0.3.0.dist-info/LICENSE
ezrest-0.3.0.dist-info/METADATA
ezrest-0.3.0.dist-info/WHEEL
ezrest-0.3.0.dist-info/top_level.txt
ezrest-0.3.0.dist-info/RECORD
