Metadata-Version: 2.1
Name: ezrest
Version: 0.3.0
Summary: Modular Python framework for implementing REST API clients
Author: Jacek Lewański
License: MIT License
Project-URL: Homepage, https://github.com/nullJaX/ezrest
Project-URL: Documentation, https://nullJaX.github.io/ezrest
Project-URL: Issues, https://github.com/nullJaX/ezrest/issues
Project-URL: Release notes, https://github.com/nullJaX/ezrest/releases
Keywords: rest,api,client,framework,ezrest
Classifier: Development Status :: 5 - Production/Stable
Classifier: Intended Audience :: Developers
Classifier: License :: OSI Approved :: MIT License
Classifier: Operating System :: OS Independent
Classifier: Programming Language :: Python :: 3
Classifier: Topic :: Software Development
Classifier: Typing :: Typed
Requires-Python: >=3.8
License-File: LICENSE
Provides-Extra: dev
Requires-Dist: build ; extra == 'dev'
Requires-Dist: httpx ; extra == 'dev'
Requires-Dist: mypy ; extra == 'dev'
Requires-Dist: pytest ; extra == 'dev'
Requires-Dist: pytest-asyncio ; extra == 'dev'
Requires-Dist: pytest-cov ; extra == 'dev'
Requires-Dist: ruff ; extra == 'dev'
Requires-Dist: twine ; extra == 'dev'
